models/__init__.py
models/transformers.py
models/utils.py
m24842_models-0.1.18.dist-info/METADATA
m24842_models-0.1.18.dist-info/WHEEL
m24842_models-0.1.18.dist-info/top_level.txt
m24842_models-0.1.18.dist-info/RECORD
