Metadata-Version: 2.4
Name: m24842_models
Version: 0.1.18
Requires-Python: >=3.8
Requires-Dist: torch
Requires-Dist: einops
Requires-Dist: opt_einsum
Requires-Dist: rotary_embedding_torch
